Coding Exercises/A23_Coding_Exercise/Coding_Exercise_A23_Always_Block/Coding_Exercise_A23_Always_Block.srcs/sim_1/new/test.sv
`timescale 1ns / 1ps
//////////////////////////////////////////////////////////////////////////////////
// Company: 
// Engineer: 
// 
// Create Date: 08/11/2025 10:24:04 PM
// Design Name: 
// Module Name: test
// Project Name: 
// Target Devices: 
// Tool Versions: 
// Description: 
// 
// Dependencies: 
// 
// Revision:
// Revision 0.01 - File Created
// Additional Comments:
// 
//////////////////////////////////////////////////////////////////////////////////
`timescale 1ns/1ps
 
 ////Do not change any code after this ->

module test(input probe);

  realtime st = 0,ed = 0;
  realtime dif = 0;

  initial begin
    @(posedge probe);
    st = $realtime();
    @(posedge probe);
    ed = $realtime();
    #2;
    dif = ed - st;
    $display("---------------------------");
    $display("magic_no = %0t", (dif/1000));
    $display("---------------------------");
  end
  
endmodule

Coding Exercises/A23_Coding_Exercise/Coding_Exercise_A23_Always_Block/Coding_Exercise_A23_Always_Block.srcs/sim_1/new/test_tb.sv
`include "test.sv"
`timescale 1ns/1ps

module test_tb();
  
  reg rst  = 0;   //////rst represent DUT reset Signal
  bit clk = 0;   //////clk represent DUT Clock Signal
  
  
  /////// User code for generating clock goes here
  ///// Generate 25 MHz Clock stimulus for signal clk with 50% Duty cycle
  initial begin
    rst = 1'b0;
    clk = 1'b0;
  end
  
  always #20 clk = ~clk;

  /////// User code ends here
 
 
  /////Do not change any code after this ->
  
  test t(clk);
  
 initial 
   begin
    $dumpfile("dump.vcd"); 
    $dumpvars;
    #400;
    $stop;
  end
  
  
endmodule

Coding Exercises/A23_Coding_Exercise/Coding_Exercise_A23_Always_Block/Coding_Exercise_A23_Always_Block.sim/sim_1/behav/xsim/dump.vcd
$date
   Mon Aug 11 22:27:31 2025
$end

$version
  2023.2
  $dumpfile ("dump.vcd") 
$end

$timescale
  1ps
$end

$scope module test_tb $end
$var reg 1 ! rst $end
$var reg 1 " clk $end
$scope module t $end
$var wire 1 # probe $end
$var real 32 $ st $end
$var real 32 % ed $end
$var real 32 & dif $end
$upscope $end
$upscope $end
$enddefinitions $end

#0
$dumpvars
0!
0"
0#
r0 $
r0 %
r0 &
$end

#20000
1"
1#
r20 $

#40000
0"
0#

#60000
1"
1#
r60 %

#62000
r40 &

#80000
0"
0#

#100000
1"
1#

#120000
0"
0#

#140000
1"
1#

#160000
0"
0#

#180000
1"
1#

#200000
0"
0#

#220000
1"
1#

#240000
0"
0#

#260000
1"
1#

#280000
0"
0#

#300000
1"
1#

#320000
0"
0#

#340000
1"
1#

#360000
0"
0#

#380000
1"
1#
